{
    "averageannualrunoffdepth": "averageannualrunoffdepth",
    "averageprecipitation": "averageprecipitation",
    "averageriverdrop": "averageriverdrop",
    "avg_exp_yd": "avgExpYd",
    "cityregioncode": "cityregioncode",
    "cityregionname": "cityregionname",
    "con_irr_a": "conIrrA",
    "cons_cond": "consCond",
    "des_int": "desInt",
    "des_q": "desQ",
    "drainagearea": "drainagearea",
    "eng_man_cd": "engManCd",
    "eng_man_name": "engManName",
    "event_time": "eventTime",
    "expr_date": "exprDate",
    "from_int_dt": "fromIntDt",
    "grwa_type": "grwaType",
    "gwhs_lat": "gwhsLat",
    "gwhs_loc": "gwhsLoc",
    "gwhs_long": "gwhsLong",
    "gws_a": "gwsA",
    "gws_cd": "gwsCd",
    "gws_nm": "gwsNm",
    "int_cd": "intCd",
    "int_nm": "intNm",
    "int_tp": "intTp",
    "is_emg": "isEmg",
    "management_agency": "managementAgency",
    "mon_g": "monG",
    "nt": "nt",
    "pdate": "pdate",
    "perm_int": "permInt",
    "perm_ww": "permWw",
    "proo_land_area": "prooLandArea",
    "proo_water_area": "prooWaterArea",
    "provregioncode": "provregioncode",
    "provregionname": "provregionname",
    "put_prod_tm": "putProdTm",
    "qsk_number": "qskNumber",
    "rang_desc": "rangDesc",
    "regioncode": "regioncode",
    "regionname": "regionname",
    "river_lake_code": "riverLakeCode",
    "river_lake_length": "riverLakeLength",
    "river_lake_name": "riverLakeName",
    "run_cond": "runCond",
    "run_year": "runYear",
    "rv_code": "rvCode",
    "rv_name": "rvName",
    "scal_type": "scalType",
    "src_dep": "srcDep",
    "src_sys": "srcSys",
    "swhs_lat": "swhsLat",
    "swhs_loc": "swhsLoc",
    "swhs_long": "swhsLong",
    "sws_cd": "swsCd",
    "sws_nm": "swsNm",
    "sws_tp": "swsTp",
    "ts": "ts",
    "wain_flow": "wainFlow",
    "wain_lat": "wainLat",
    "wain_loc": "wainLoc",
    "wain_long": "wainLong",
    "wain_use": "wainUse",
    "wain_waso_name": "wainWasoName",
    "wain_waso_type": "wainWasoType",
    "waqu_goal": "waquGoal",
    "waso_type": "wasoType",
    "wasu_town_name": "wasuTownName",
    "wat_lic_code": "watLicCode",
    "well_nums": "wellNums",
    "whs_appr_cd": "whsApprCd",
    "whs_man_cd": "whsManCd",
    "whs_man_name": "whsManName",
    "ws_obj": "wsObj",
    "ws_obj_tp": "wsObjTp",
    "ws_reg": "wsReg"
}
